l2m2/__init__.py
l2m2/exceptions.py
l2m2/model_info.py
l2m2/py.typed
l2m2/warnings.py
l2m2/_internal/__init__.py
l2m2/_internal/http.py
l2m2/client/__init__.py
l2m2/client/async_llm_client.py
l2m2/client/base_llm_client.py
l2m2/client/llm_client.py
l2m2/memory/__init__.py
l2m2/memory/base_memory.py
l2m2/memory/chat_memory.py
l2m2/memory/external_memory.py
l2m2/tools/__init__.py
l2m2/tools/json_mode_strategies.py
l2m2/tools/prompt_loader.py
l2m2-0.0.62.dist-info/licenses/LICENSE
l2m2-0.0.62.dist-info/METADATA
l2m2-0.0.62.dist-info/WHEEL
l2m2-0.0.62.dist-info/top_level.txt
l2m2-0.0.62.dist-info/RECORD
