Metadata-Version: 2.4
Name: l2m2
Version: 0.0.62
Summary: A very simple LLM manager for Python.
Author-email: Pierce Kelaita <pierce@kelaita.com>
License-Expression: MIT
Project-URL: Homepage, https://github.com/pkelaita/l2m2
Project-URL: Documentation, https://github.com/pkelaita/l2m2/blob/main/README.md
Project-URL: Repository, https://github.com/pkelaita/l2m2.git
Project-URL: Issues, https://github.com/pkelaita/l2m2/issues
Requires-Python: >=3.10
License-File: LICENSE
Requires-Dist: aiohttp>=3.13.1
Dynamic: license-file
